multiexit.py
multiexit-1.4.1.dist-info/METADATA
multiexit-1.4.1.dist-info/RECORD
multiexit-1.4.1.dist-info/WHEEL
multiexit-1.4.1.dist-info/top_level.txt
