Metadata-Version: 2.1
Name: multiexit
Version: 1.4.1
Summary: atexit replacement that supports multiprocessing
Home-page: https://github.com/kuralabs/multiexit
Author: KuraLabs S.R.L
Author-email: info@kuralabs.io
License: UNKNOWN
Keywords: multiexit multiprocessing atexit
Platform: UNKNOWN
Classifier: Development Status :: 3 - Alpha
Classifier: Intended Audience :: Developers
Classifier: License :: OSI Approved :: Apache Software License
Classifier: Natural Language :: English
Classifier: Operating System :: POSIX :: Linux
Classifier: Programming Language :: Python :: 3
